{"year-stat":[{"year":"2009","num":2},{"year":"2010","num":0},{"year":"2011","num":1}],"author":{"ee":["http:\/\/ceur-ws.org\/Vol-1175\/CLEF2009wn-INFILE-DragusanuEt2009.pdf","https:\/\/doi.org\/10.1007\/978-3-642-15754-7_43","http:\/\/www.clef-initiative.eu\/documents\/71612\/86377\/CLEF2011wn-PAN-DragusanuEt2011.pdf"],"name":"Cristian-Alexandru Dragusanu","publications":["UAIC: Participation in INFILE@CLEF Task.","UAIC: Participation in INFILE@CLEF Task.","Detecting Wikipedia Vandalism using Machine Learning - Notebook for PAN at CLEF 2011."]},"coauthor-stat":[{"coauthor":"Adrian Iftene","num":3},{"coauthor":"Alecsandru Grigoriu","num":2},{"coauthor":"Dan Anton","num":1},{"coauthor":"Daniela Epure","num":1},{"coauthor":"Andreea-Loredana Andresan","num":1}]}