{"year-stat":[{"year":"2004","num":2},{"year":"2005","num":0},{"year":"2006","num":0},{"year":"2007","num":0},{"year":"2008","num":0},{"year":"2009","num":0},{"year":"2010","num":0},{"year":"2011","num":0},{"year":"2012","num":0},{"year":"2013","num":0},{"year":"2014","num":0},{"year":"2015","num":0},{"year":"2016","num":0},{"year":"2017","num":1}],"author":{"ee":["https:\/\/doi.org\/10.1007\/978-3-319-65813-1_4","http:\/\/ceur-ws.org\/Vol-1170\/CLEF2004wn-ImageCLEF-JonesEt2004.pdf","https:\/\/doi.org\/10.1007\/11519645_64"],"name":"Andy Way","publications":["Improving the Reliability of Query Expansion for User-Generated Speech Retrieval Using Query Performance Prediction.","Dublin City University at CLEF 2004: Experiments with the ImageCLEF St Andrew's Collection.","Dublin City University at CLEF 2004: Experiments with the ImageCLEF St. Andrew's Collection."]},"coauthor-stat":[{"coauthor":"Gareth J. F. Jones","num":3},{"coauthor":"Adenike M. Lam-Adesina","num":2},{"coauthor":"Anna Khasin","num":2},{"coauthor":"Bart Mellebeek","num":2},{"coauthor":"Declan Groves","num":2}]}