{"year-stat":[{"year":"2006","num":2}],"author":{"ee":["https:\/\/doi.org\/10.1007\/978-3-540-74999-8_54","http:\/\/ceur-ws.org\/Vol-1172\/CLEF2006wn-QACLEF-GrauEt2006.pdf"],"name":"Michael Bagur","publications":["The Bilingual System MUSCLEF at QA@CLEF 2006.","The Bilingual System MUSCLEF at QA@CLEF 2006."]},"coauthor-stat":[{"coauthor":"Anne-Laure Ligozat","num":2},{"coauthor":"Brigitte Grau","num":2},{"coauthor":"Isabelle Robba","num":2},{"coauthor":"K&eacute;vin S&eacute;journ&eacute;","num":2},{"coauthor":"Anne Vilnat","num":2}]}