{"year-stat":[{"year":"2013","num":1},{"year":"2014","num":1}],"author":{"ee":["http:\/\/ceur-ws.org\/Vol-1179\/CLEF2013wn-PAN-WilliamsEt2013.pdf","http:\/\/ceur-ws.org\/Vol-1180\/CLEF2014wn-Pan-WilliamsEt2014.pdf"],"name":"Kyle Williams","publications":["Unsupervised Ranking for Plagiarism Source Retrieval Notebook for PAN at CLEF 2013.","Supervised Ranking for Plagiarism Source Retrieval."]},"coauthor-stat":[{"coauthor":"Hung-Hsuan Chen","num":2},{"coauthor":"C. Lee Giles","num":2},{"coauthor":"Sagnik Ray Choudhury","num":1}]}