{"year-stat":[{"year":"2005","num":2}],"author":{"ee":["http:\/\/ceur-ws.org\/Vol-1171\/CLEF2005wn-WebCLEF-JensenEt2005.pdf","https:\/\/doi.org\/10.1007\/11878773_91"],"name":"Niels Jensen","publications":["Web Retrieval Experiments with the EuroGOV Corpus at the University of Hildesheim.","Web Retrieval Experiments with the EuroGOV Corpus at the University of Hildesheim."]},"coauthor-stat":[{"coauthor":"Thomas Mandl 0001","num":2},{"coauthor":"Robert Str&ouml;tgen","num":2},{"coauthor":"Ren&eacute; Hackl","num":2}]}