{"year-stat":[{"year":"2012","num":1},{"year":"2013","num":1}],"author":{"ee":["http:\/\/ceur-ws.org\/Vol-1179\/CLEF2013wn-INEX-CrouchEt2013.pdf","http:\/\/www.clef-initiative.eu\/documents\/71612\/9c4e5b24-268e-4e17-857e-300a2d0a6a2e"],"name":"Swapnil Nawale","publications":["Refining Methodologies for the INEX 2013 Snippet Generation and Tweet Contextualization Tracks.","The 2012 INEX Snippet and Tweet Contextualization Tasks."]},"coauthor-stat":[{"coauthor":"Donald B. Crouch","num":2},{"coauthor":"Sameer Kulkarni","num":2},{"coauthor":"Carolyn J. Crouch","num":2},{"coauthor":"Sai Chittilla","num":1},{"coauthor":"Mihir Atmakuri","num":1}]}