{"year-stat":[{"year":"2004","num":2},{"year":"2005","num":0},{"year":"2006","num":2},{"year":"2007","num":1},{"year":"2008","num":2}],"author":{"ee":["http:\/\/ceur-ws.org\/Vol-1173\/CLEF2007wn-WebCLEF-Adafre2007.pdf","https:\/\/doi.org\/10.1007\/978-3-642-04447-2_41","https:\/\/doi.org\/10.1007\/11519645_12","http:\/\/ceur-ws.org\/Vol-1170\/CLEF2004wn-adhoc-FissahaAdafreEt2004.pdf","http:\/\/ceur-ws.org\/Vol-1172\/CLEF2006wn-QACLEF-AdafreEt2006.pdf","https:\/\/doi.org\/10.1007\/978-3-540-74999-8_65","http:\/\/ceur-ws.org\/Vol-1174\/CLEF2008wn-QACLEF-AdafreEt2008.pdf"],"name":"Sisay Fissaha Adafre","publications":["Dublin City University at WebCLEF 2007.","Dublin City University at QA@CLEF 2008.","Effective Translation, Tokenization and Combination for Cross-Lingual Retrieval.","The University of Amsterdam at CLEF 2004.","The University of Amsterdam at WiQA 2006.","Link-Based vs. Content-Based Retrieval for Question Answering Using Wikipedia.","Dublin City University at QA@CLEF 2008."]},"coauthor-stat":[{"coauthor":"Maarten de Rijke","num":4},{"coauthor":"Jaap Kamps","num":2},{"coauthor":"Valentin Jijkoun","num":2},{"coauthor":"Josef van Genabith","num":2},{"coauthor":"Willem Robert van Hage","num":1}]}