{"year-stat":[{"year":"2008","num":2},{"year":"2009","num":4}],"author":{"ee":["http:\/\/ceur-ws.org\/Vol-1175\/CLEF2009wn-QACLEF-AgirreEt2009.pdf","http:\/\/ceur-ws.org\/Vol-1175\/CLEF2009wn-adhoc-AgirreEt2009b.pdf","http:\/\/ceur-ws.org\/Vol-1174\/CLEF2008wn-adhoc-PerezAgueraEt2008.pdf","https:\/\/www.wikidata.org\/entity\/Q57400832","https:\/\/www.wikidata.org\/entity\/Q57400830","https:\/\/doi.org\/10.1007\/978-3-642-04447-2_17"],"name":"Hugo Zaragoza","publications":["Elhuyar-IXA: Semantic Relatedness and Cross-lingual Passage Retrieval.","Using Semantic Relatedness and Word Sense Disambiguation for (CL)IR.","UCM-Y!R at CLEF 2008 Robust and WSD tasks.","Using Semantic Relatedness and Word Sense Disambiguation for (CL)IR.","Elhuyar-IXA: Semantic Relatedness and Cross-Lingual Passage Retrieval.","Query Clauses and Term Independence."]},"coauthor-stat":[{"coauthor":"Eneko Agirre","num":4},{"coauthor":"Arantxa Otegi","num":4},{"coauthor":"Olatz Ansa","num":2},{"coauthor":"Xabier Saralegi","num":2},{"coauthor":"Jos&eacute; R. P&eacute;rez-Ag&uuml;era","num":2}]}