{"year-stat":[{"year":"2013","num":2},{"year":"2014","num":0},{"year":"2015","num":0},{"year":"2016","num":0},{"year":"2017","num":2},{"year":"2018","num":1}],"author":{"ee":["http:\/\/ceur-ws.org\/Vol-1179\/CLEF2013wn-CLEFeHealth-ZucconEt2013.pdf","http:\/\/ceur-ws.org\/Vol-1866\/paper_91.pdf","http:\/\/ceur-ws.org\/Vol-1179\/CLEF2013wn-CLEFeHealth-ZucconEt2013b.pdf","http:\/\/ceur-ws.org\/Vol-2125\/paper_203.pdf","http:\/\/ceur-ws.org\/Vol-1866\/paper_98.pdf"],"name":"Bevan Koopman","publications":["Identify Disorders in Health Records using Conditional Random Fields and Metamap AEHRC at ShARe\/CLEF 2013 eHealth Evaluation Lab Task 1.","QUT ielab at CLEF 2017 e-Health IR Task: Knowledge Base Retrieval for Consumer Health Search.","Retrieval of Health Advice on the Web AEHRC at ShARe\/CLEF eHealth Evaluation Lab Task 3.","QUT IElab at CLEF 2018 Consumer Health Search Task: Knowledge Base Retrieval for Consumer Health Search.","QUT ielab at CLEF 2017 Technology Assisted Reviews Track: Initial Experiments with Learning To Rank."]},"coauthor-stat":[{"coauthor":"Guido Zuccon","num":5},{"coauthor":"Jimmy","num":2},{"coauthor":"Anthony N. Nguyen","num":2},{"coauthor":"Harrisen Scells","num":1},{"coauthor":"Alexander Holloway","num":1}]}