{"year-stat":[{"year":"2001","num":2},{"year":"2002","num":0},{"year":"2003","num":0},{"year":"2004","num":0},{"year":"2005","num":0},{"year":"2006","num":0},{"year":"2007","num":0},{"year":"2008","num":0},{"year":"2009","num":0},{"year":"2010","num":0},{"year":"2011","num":0},{"year":"2012","num":0},{"year":"2013","num":0},{"year":"2014","num":1},{"year":"2015","num":1}],"author":{"ee":["http:\/\/ceur-ws.org\/Vol-1180\/CLEF2014wn-eHealth-ThesprasithtEt2014.pdf","http:\/\/ceur-ws.org\/Vol-1167\/CLEF2001wn-adhoc-Chuleerat2001.pdf","https:\/\/doi.org\/10.1007\/3-540-45691-0_18","http:\/\/ceur-ws.org\/Vol-1391\/73-CR.pdf"],"name":"Chuleerat Jaruskulchai","publications":["CSKU GPRF-QE for Medical Topic Web Retrieval.","Dictionary-based Thai CLIR: Experimental Survey of Thai CLIR.","Dictionary-Based Thai CLIR: An Experimental Survey of Thai CLIR.","Task 2a: Team KU-CS: Query Coherence Analysis for PRF and Genomics Expansion."]},"coauthor-stat":[{"coauthor":"Ornuma Thesprasith","num":2}]}