{"year-stat":[{"year":"2010","num":1},{"year":"2011","num":0},{"year":"2012","num":0},{"year":"2013","num":1},{"year":"2014","num":0},{"year":"2015","num":1},{"year":"2016","num":0},{"year":"2017","num":0},{"year":"2018","num":1}],"author":{"ee":["http:\/\/ceur-ws.org\/Vol-1179\/CLEF2013wn-PAN-PatraEt2013.pdf","http:\/\/ceur-ws.org\/Vol-1391\/134-CR.pdf","http:\/\/www.clef-initiative.eu\/documents\/71612\/86374\/CLEF2010wn-MLQA10-PakrayEt2010.pdf","http:\/\/ceur-ws.org\/Vol-2125\/paper_115.pdf"],"name":"Dipankar Das 0001","publications":["Automatic Author Profiling Based on Linguistic and Stylistic Features Notebook for PAN at CLEF 2013.","Authorship Verification: An Approach based on Random Forest: Notebook for PAN at CLEF 2015.","JU_CSE_TE: System Description QA@CLEF 2010 - ResPubliQA.","Multimodal Author Profiling for Twitter: Notebook for PAN at CLEF 2018."]},"coauthor-stat":[{"coauthor":"Sivaji Bandyopadhyay","num":2},{"coauthor":"Braja Gopal Patra","num":2},{"coauthor":"Promita Maitra","num":1},{"coauthor":"Tanik Saikh","num":1},{"coauthor":"Pinaki Bhaskar","num":1}]}