{"year-stat":[{"year":"2017","num":1},{"year":"2018","num":3}],"author":{"ee":["http:\/\/ceur-ws.org\/Vol-1866\/paper_143.pdf","http:\/\/ceur-ws.org\/Vol-2125\/paper_85.pdf","http:\/\/ceur-ws.org\/Vol-2125\/paper_92.pdf","http:\/\/ceur-ws.org\/Vol-2125\/paper_93.pdf"],"name":"Danny Kowerko","publications":["Large-Scale Bird Sound Classification using Convolutional Neural Networks.","A Baseline for Large-Scale Bird Species Identification in Field Recordings.","Large-Scale Plant Classification using Deep Convolutional Neural Networks.","Species Prediction based on Environmental Variables using Machine Learning Techniques."]},"coauthor-stat":[{"coauthor":"Maximilian Eibl","num":4},{"coauthor":"Stefan Kahl","num":4},{"coauthor":"Holger Klinck","num":2},{"coauthor":"Thomas Wilhelm-Stein","num":2},{"coauthor":"Hussein Hussein","num":1}]}