{"year-stat":[{"year":"2008","num":2},{"year":"2009","num":2}],"author":{"ee":["https:\/\/doi.org\/10.1007\/978-3-642-04447-2_79","http:\/\/ceur-ws.org\/Vol-1174\/CLEF2008wn-ImageCLEF-OverellEt2008.pdf","http:\/\/ceur-ws.org\/Vol-1175\/CLEF2009wn-ImageCLEF-LlorenteEt2009.pdf","https:\/\/doi.org\/10.1007\/978-3-642-15751-6_40"],"name":"Ainhoa Llorente","publications":["Exploiting Term Co-occurrence for Enhancing Automated Image Annotation.","MMIS at ImageCLEF 2008: Experiments combining Different Evidence Sources.","MMIS at ImageCLEF 2009: Non-parametric Density Estimation Algorithms.","Exploring the Semantics behind a Collection to Improve Automated Image Annotation."]},"coauthor-stat":[{"coauthor":"Stefan M. R&uuml;ger","num":4},{"coauthor":"Dawei Song 0001","num":2},{"coauthor":"Haiming Liu 0002","num":2},{"coauthor":"Rui Hu","num":2},{"coauthor":"Simon E. Overell","num":2}]}