{"year-stat":[{"year":"2004","num":2},{"year":"2005","num":4},{"year":"2006","num":3},{"year":"2007","num":4},{"year":"2008","num":4},{"year":"2009","num":2}],"author":{"ee":["http:\/\/ceur-ws.org\/Vol-1172\/CLEF2006wn-GeoCLEF-GeyEt2006.pdf","http:\/\/ceur-ws.org\/Vol-1175\/CLEF2009wn-QACLEF-SantosEt2009.pdf","http:\/\/ceur-ws.org\/Vol-1174\/CLEF2008wn-GeoCLEF-SantosEt2008.pdf","https:\/\/doi.org\/10.1007\/11878773_36","https:\/\/doi.org\/10.1007\/978-3-642-04447-2_118","http:\/\/ceur-ws.org\/Vol-1173\/CLEF2007wn-QACLEF-CabralEt2007.pdf","https:\/\/doi.org\/10.1007\/978-3-540-85760-0_31","https:\/\/doi.org\/10.1007\/11519645_80","https:\/\/doi.org\/10.1007\/978-3-540-74999-8_109","https:\/\/doi.org\/10.1007\/978-3-642-04447-2_106","https:\/\/doi.org\/10.1007\/978-3-540-74999-8_70","http:\/\/ceur-ws.org\/Vol-1174\/CLEF2008wn-GeoCLEF-MandlEt2008.pdf","https:\/\/doi.org\/10.1007\/11878773_112","https:\/\/doi.org\/10.1007\/978-3-540-85760-0_96","http:\/\/ceur-ws.org\/Vol-1171\/CLEF2005wn-adhoc-SantosEt2005.pdf","http:\/\/ceur-ws.org\/Vol-1171\/CLEF2005wn-QACLEF-VallinEt2005.pdf","http:\/\/ceur-ws.org\/Vol-1170\/CLEF2004wn-other-Santos2004.pdf","https:\/\/doi.org\/10.1007\/978-3-642-15754-7_23","http:\/\/ceur-ws.org\/Vol-1173\/CLEF2007wn-GeoCLEF-MandlEt2007.pdf"],"name":"Diana Santos","publications":["GeoCLEF 2006: the CLEF 2006 Cross-Language Geographic Information Retrieval Track Overview.","GikiCLEF: Crosscultural Issues in an International Setting: Asking non-English-centered Questions to Wikipedia.","Getting Geographical Answers fromWikipedia: the GikiP pilot at CLEF.","Overview of the CLEF 2005 Multilingual Question Answering Track.","GikiP at GeoCLEF 2008: Joining GIR and QA Forces for Querying Wikipedia.","Esfinge at CLEF 2007: First Steps in a Multiple Question and Multiple Answer Approach.","What Happened to Esfinge in 2007?","The Key to the First CLEF with Portuguese: Topics, Questions and Answers in CHAVE.","GeoCLEF 2006: The CLEF 2006 Cross-Language Geographic Information Retrieval Track Overview.","GeoCLEF 2008: The CLEF 2008 Cross-Language Geographic Information Retrieval Track Overview.","QolA: Fostering Collaboration Within QA.","GeoCLEF 2008: the CLEF 2008 Cross-Language Geographic Information Retrieval Track Overview.","Portuguese at CLEF 2005.","GeoCLEF 2007: The CLEF 2007 Cross-Language Geographic Information Retrieval Track Overview.","Portuguese at CLEF 2005: Reflections and Challenges.","Overview of the CLEF 2005 Multilingual Question Answering Track.","CHAVE: Topics and Questions on the Portuguese Participation in CLEF.","GikiCLEF: Expectations and Lessons Learned.","GeoCLEF 2007: the CLEF 2007 Cross-Language Geographic Information Retrieval Track Overview."]},"coauthor-stat":[{"coauthor":"Fredric C. Gey","num":6},{"coauthor":"Christa Womser-Hacker","num":6},{"coauthor":"Thomas Mandl 0001","num":6},{"coauthor":"Ray R. Larson","num":6},{"coauthor":"Giorgio Maria Di Nunzio","num":5}]}