{"year-stat":[{"year":"2010","num":2},{"year":"2011","num":0},{"year":"2012","num":1}],"author":{"ee":["http:\/\/www.clef-initiative.eu\/documents\/71612\/3a0661d9-78f0-4eb1-8a96-19d898f40fb3","http:\/\/www.clef-initiative.eu\/documents\/71612\/86374\/CLEF2010wn-ImageCLEF-ClinchantEt2010.pdf","http:\/\/www.clef-initiative.eu\/documents\/71612\/86374\/CLEF2010wn-ImageCLEF-MensinkEt2010.pdf"],"name":"Jorge S&aacute;nchez","publications":["Leveraging Robust Signatures for Mobile Robot Semantic Localization.","XRCE's Participation in Wikipedia Retrieval, Medical Image Modality Classification and Ad-hoc Retrieval Tasks of ImageCLEF 2010.","LEAR and XRCE's Participation to Visual Concept Detection Task - ImageCLEF 2010."]},"coauthor-stat":[{"coauthor":"Gabriela Csurka","num":2},{"coauthor":"Florent Perronnin","num":2},{"coauthor":"Javier Redolfi","num":1},{"coauthor":"Guillaume Jacquet","num":1},{"coauthor":"Julien Ah-Pine","num":1}]}